mosaic_spec/__init__.py
mosaic_spec-0.0.0.dist-info/METADATA
mosaic_spec-0.0.0.dist-info/WHEEL
mosaic_spec-0.0.0.dist-info/top_level.txt
mosaic_spec-0.0.0.dist-info/RECORD
