Metadata-Version: 2.1
Name: mosaic-spec
Version: 0.0.0
Provides-Extra: dev
Requires-Dist: pytest ; extra == 'dev'
Requires-Dist: flake8 ; extra == 'dev'
Requires-Dist: invoke ; extra == 'dev'
Requires-Dist: twine ; extra == 'dev'
